shift_reg.vhdl
library ieee;
use ieee.std_logic_1164.all;

entity shift_reg is
port(	I:	in std_logic_vector (3 downto 0); -- for loading
		I_SHIFT_IN: in std_logic; -- shifted in bit for both left and right
		sel:        in std_logic_vector(1 downto 0); -- 00:hold; 01: shift left; 10: shift right; 11: load
		clock:		in std_logic; -- positive level triggering in problem 3
		enable:		in std_logic; -- 0: don't do anything; 1: shift_reg is enabled
		O:	out std_logic_vector(3 downto 0) -- output the current register content. HINT: should be combinational.
		-- SHIFT_OUT : out std_logic;
);
end shift_reg;

architecture behav of shift_reg is
signal values : std_logic_vector (3 downto 0);	--saved values before it gets loaded into O
begin

process(I, I_SHIFT_IN, sel, enable, clock) is
begin
	if (clock='1' and enable='1') then
		if (sel="00") then
			-- do nothing
			O(3) <= values(3);
			O(2) <= values(2);
			O(1) <= values(1);
			O(0) <= values(0);
		
		elsif (sel ="01") then
			O(3) <= values(2);
			O(2) <= values(1);
			O(1) <= values(0);
			O(0) <= I_SHIFT_IN;
			values(3) <= values(2);
			values(2) <= values(1);
			values(1) <= values(0);
			values(0) <= I_SHIFT_IN;

		elsif (sel="10") then
			O(3) <= I_SHIFT_IN;
			O(2) <= values(3);
			O(1) <= values(2);
			O(0) <= values(1);
			values(0) <= values(1);
			values(1) <= values(2);
			values(2) <= values(3);
			values(3) <= I_SHIFT_IN;
		
		elsif (sel="11") then
			O(3) <= I(3);
			O(2) <= I(2);
			O(1) <= I(1);
			O(0) <= I(0);
			values(0) <= I(0);
			values(1) <= I(1);
			values(2) <= I(2);
			values(3) <= I(3);
		end if;
		
		
	end if;
end process;

end behav;

shift_reg_8bit.vhdl
library ieee;
use ieee.std_logic_1164.all;

entity shift_reg_8bit is
port(	I_8bit:	in std_logic_vector (7 downto 0); -- for loading
		I_SHIFT_IN_8bit: in std_logic; -- shifted in bit for both left and right
		sel_8bit:        in std_logic_vector(1 downto 0); -- 00:hold; 01: shift left; 10: shift right; 11: load
		clock_8bit:		in std_logic; -- positive level triggering in problem 3
		enable_8bit:		in std_logic; -- 0: don't do anything; 1: shift_reg is enabled
		O_8bit:	out std_logic_vector(7 downto 0) -- output the current register content. HINT: should be combinational.
		-- SHIFT_OUT : out std_logic;
);
end shift_reg_8bit;


architecture behav of shift_reg_8bit is

component shift_reg
port (	I:	in std_logic_vector (3 downto 0);
        I_SHIFT_IN: in std_logic;
        sel:        in std_logic_vector(1 downto 0); -- 00:hold; 01: shift left; 10: shift right; 11: load
        clock:		in std_logic; 
        enable:		in std_logic;
        O:	out std_logic_vector(3 downto 0)
);
end component;

signal values_8bit : std_logic_vector (7 downto 0);	--saved values before it gets loaded into O
signal inshift0: std_logic;
signal inshift1: std_logic;
begin

--  Component instantiation.
shift_reg_0: shift_reg port map (I => I_8bit(7 downto 4), I_SHIFT_IN => inshift0, sel => sel_8bit, clock => clock_8bit, enable => enable_8bit, O => O_8bit(7 downto 4)); --left 4 bits
shift_reg_1: shift_reg port map (I => I_8bit(3 downto 0), I_SHIFT_IN => inshift1, sel => sel_8bit, clock => clock_8bit, enable => enable_8bit, O => O_8bit(3 downto 0)); --right 4 bits

process(I_8bit, I_SHIFT_IN_8bit, sel_8bit, enable_8bit, clock_8bit) is
begin
	if (clock_8bit='1' and enable_8bit='1') then
		if (sel_8bit="00") then
			inshift0 <= I_SHIFT_IN_8bit;
            inshift1 <= I_SHIFT_IN_8bit;
			-- do nothing
            --O_8bit <= values;

		elsif (sel_8bit ="01") then --left shift
            --write to a mux values(3) and send it in I_SHIFT_IN
            inshift0 <= values_8bit(3);
            inshift1 <= I_SHIFT_IN_8bit;
			values_8bit(7) <= values_8bit(6);
			values_8bit(6) <= values_8bit(5);
			values_8bit(5) <= values_8bit(4);
			values_8bit(4) <= values_8bit(3);
			values_8bit(3) <= values_8bit(2);
			values_8bit(2) <= values_8bit(1);
			values_8bit(1) <= values_8bit(0);
			values_8bit(0) <= I_SHIFT_IN_8bit;
            --O_8bit <= values;
            
		elsif (sel_8bit="10") then --right shift
			inshift0 <= I_SHIFT_IN_8bit;
            inshift1 <= values_8bit(4);
			values_8bit(0) <= values_8bit(1);
			values_8bit(1) <= values_8bit(2);
			values_8bit(2) <= values_8bit(3);
			values_8bit(3) <= values_8bit(4);
			values_8bit(4) <= values_8bit(5);
			values_8bit(5) <= values_8bit(6);
			values_8bit(6) <= values_8bit(7);
			values_8bit(7) <= I_SHIFT_IN_8bit;

            --O_8bit <= values;
		elsif (sel_8bit="11") then
			inshift0 <= I_SHIFT_IN_8bit;
            inshift1 <= I_SHIFT_IN_8bit;
			--O_8bit <= I_8bit;
            values_8bit <= I_8bit;
		end if;
		
		
	end if;
end process;

end behav;

shift_reg_8bit_tb.vhdl
library ieee;
use ieee.std_logic_1164.all;

--  A testbench has no ports.
entity shift_reg_8bit_tb is
end shift_reg_8bit_tb;

architecture behav of shift_reg_8bit_tb is
--  Declaration of the component that will be instantiated.
component shift_reg_8bit
port (	I_8bit:	in std_logic_vector (7 downto 0);
		I_SHIFT_IN_8bit: in std_logic;
		sel_8bit:        in std_logic_vector(1 downto 0); -- 00:hold; 01: shift left; 10: shift right; 11: load
		clock_8bit:		in std_logic; 
		enable_8bit:		in std_logic;
		O_8bit:	out std_logic_vector(7 downto 0)
);
end component;
--  Specifies which entity is bound with the component.
-- for shift_reg_0: shift_reg use entity work.shift_reg(rtl);
signal i, o : std_logic_vector(7 downto 0);
signal i_shift_in, clk, enable : std_logic;
signal sel : std_logic_vector(1 downto 0);
begin
--  Component instantiation.
shift_reg_8bit_0: shift_reg_8bit port map (I_8bit => i, I_SHIFT_IN_8bit => i_shift_in, sel_8bit => sel, clock_8bit => clk, enable_8bit => enable, O_8bit => o);

--  This process does the real job.
process
type pattern_type is record
--  The inputs of the shift_reg.
i: std_logic_vector (7 downto 0);
i_shift_in, clock, enable: std_logic;
sel: std_logic_vector(1 downto 0);
--  The expected outputs of the shift_reg.
o: std_logic_vector (7 downto 0);
end record;
--  The patterns to apply.
type pattern_array is array (natural range <>) of pattern_type;
constant patterns : pattern_array := --WRONG test vectors. replace with your own.

(("11000000", '0', '1', '1', "11", "11000000"),
("11000011", '0', '1', '1', "11", "11000011"),
("11111111", '0', '1', '1', "10", "01100001"),
("00000000", '0', '1', '1', "10", "00110000"),
("11111111", '0', '1', '1', "10", "00011000"),
("00000000", '0', '1', '1', "10", "00001100"),
("00000000", '0', '1', '1', "00", "00001100"),
("11111111", '0', '1', '1', "10", "00000110"),
("00000000", '0', '1', '1', "10", "00000011"),
("11111111", '0', '1', '1', "10", "00000001"),
("00000000", '0', '1', '1', "10", "00000000"),
("11000001", '0', '1', '1', "11", "11000001"),
("11000001", '1', '1', '1', "11", "11000001")); -- Need two vectors to simulate an edge.
begin
--  Check each pattern.
for n in patterns'range loop
--  Set the inputs.
i <= patterns(n).i;
i_shift_in <= patterns(n).i_shift_in;
sel <= patterns(n).sel;
clk <= patterns(n).clock;
enable <= patterns(n).enable;
--  Wait for the results.
wait for 1 ns;
--  Check the outputs.
assert o = patterns(n).o
report "bad output value" severity error;
end loop;
assert false report "end of test" severity note;
--  Wait forever; this will finish the simulation.
wait;
end process;
end behav;

shift_reg_8bit.vcd
$date
  Sun Apr 25 19:27:41 2021
$end
$version
  GHDL v0
$end
$timescale
  1 fs
$end
$scope module standard $end
$upscope $end
$scope module std_logic_1164 $end
$upscope $end
$scope module shift_reg_8bit_tb $end
$var reg 8 ! i[7:0] $end
$var reg 8 " o[7:0] $end
$var reg 1 # i_shift_in $end
$var reg 1 $ clk $end
$var reg 1 % enable $end
$var reg 2 & sel[1:0] $end
$scope module shift_reg_8bit_0 $end
$var reg 8 ' i_8bit[7:0] $end
$var reg 1 ( i_shift_in_8bit $end
$var reg 2 ) sel_8bit[1:0] $end
$var reg 1 * clock_8bit $end
$var reg 1 + enable_8bit $end
$var reg 8 , o_8bit[7:0] $end
$var reg 8 - values_8bit[7:0] $end
$var reg 1 . inshift0 $end
$var reg 1 / inshift1 $end
$scope module shift_reg_0 $end
$var reg 4 0 i[3:0] $end
$var reg 1 1 i_shift_in $end
$var reg 2 2 sel[1:0] $end
$var reg 1 3 clock $end
$var reg 1 4 enable $end
$var reg 4 5 o[3:0] $end
$var reg 4 6 values[3:0] $end
$upscope $end
$scope module shift_reg_1 $end
$var reg 4 7 i[3:0] $end
$var reg 1 8 i_shift_in $end
$var reg 2 9 sel[1:0] $end
$var reg 1 : clock $end
$var reg 1 ; enable $end
$var reg 4 < o[3:0] $end
$var reg 4 = values[3:0] $end
$upscope $end
$upscope $end
$upscope $end
$enddefinitions $end
#0
b11000000 !
b11000000 "
0#
1$
1%
b11 &
b11000000 '
0(
b11 )
1*
1+
b11000000 ,
b11000000 -
0.
0/
b1100 0
01
b11 2
13
14
b1100 5
b1100 6
b0000 7
08
b11 9
1:
1;
b0000 <
b0000 =
#1000000
b11000011 !
b11000011 "
b11000011 '
b11000011 ,
b11000011 -
b0011 7
b0011 <
b0011 =
#2000000
b11111111 !
b01100001 "
b10 &
b11111111 '
b10 )
b01100001 ,
b01100001 -
b1111 0
b10 2
b0110 5
b0110 6
b1111 7
b10 9
b0001 <
b0001 =
#3000000
b00000000 !
b00110000 "
b00000000 '
b00110000 ,
b00110000 -
b0000 0
b0011 5
b0011 6
b0000 7
b0000 <
b0000 =
#4000000
b11111111 !
b00011000 "
b11111111 '
b00011000 ,
b00011000 -
1/
b1111 0
b0001 5
b0001 6
b1111 7
18
b1000 <
b1000 =
#5000000
b00000000 !
b00001100 "
b00000000 '
b00001100 ,
b00001100 -
b0000 0
b0000 5
b0000 6
b0000 7
b1100 <
b1100 =
#6000000
b11111111 !
b00000111 "
b11111111 '
b00000111 ,
b00000110 -
0/
b1111 0
b1111 7
08
b0111 <
b0111 =
#7000000
b00000000 !
b00000011 "
b00000000 '
b00000011 ,
b00000011 -
b0000 0
b0000 7
b0011 <
b0011 =
#8000000
b11111111 !
b00000001 "
b11111111 '
b00000001 ,
b00000001 -
b1111 0
b1111 7
b0001 <
b0001 =
#9000000
b00000000 !
b00000000 "
b00000000 '
b00000000 ,
b00000000 -
b0000 0
b0000 7
b0000 <
b0000 =
#10000000
b11000001 !
b11000001 "
b11 &
b11000001 '
b11 )
b11000001 ,
b11000001 -
b1100 0
b11 2
b1100 5
b1100 6
b0001 7
b11 9
b0001 <
b0001 =
#11000000
1#
1(
1.
1/
11
18
